ps3_update_dl/__init__.py
ps3_update_dl/playstation-ca.crt
ps3_update_dl-0.3.0.post2.dist-info/LICENSE.md
ps3_update_dl-0.3.0.post2.dist-info/METADATA
ps3_update_dl-0.3.0.post2.dist-info/WHEEL
ps3_update_dl-0.3.0.post2.dist-info/entry_points.txt
ps3_update_dl-0.3.0.post2.dist-info/top_level.txt
ps3_update_dl-0.3.0.post2.dist-info/RECORD
