Metadata-Version: 2.1
Name: ps3-update-dl
Version: 0.3.0.post2
Summary: Download all updates for a given PS3 game
Home-page: https://github.com/iomintz/ps3-update-dl
Author: io mintz
Author-email: io@mintz.cc
License: AGPLv3+
Classifier: License :: OSI Approved :: GNU Affero General Public License v3 or later (AGPLv3+)
Classifier: Development Status :: 3 - Alpha
Classifier: Environment :: Console
Classifier: Intended Audience :: End Users/Desktop
Classifier: Topic :: Games/Entertainment
Classifier: Topic :: System :: Emulators
Classifier: Topic :: Utilities
Classifier: Natural Language :: English
Classifier: Operating System :: OS Independent
Classifier: Programming Language :: Python :: 3
Classifier: Programming Language :: Python :: 3 :: Only
Classifier: Programming Language :: Python :: 3.7
Classifier: Programming Language :: Python :: 3.8
Classifier: Programming Language :: Python :: 3.9
Classifier: Programming Language :: Python :: Implementation
Classifier: Programming Language :: Python :: Implementation :: CPython
Requires-Python: >=3.7.0
License-File: LICENSE.md
Requires-Dist: requests <3.0.0,>=2.23.0
Requires-Dist: tqdm <5.0.0,>=4.49.0
Requires-Dist: PyYAML <6.0.0,>=5.4.1
